.gitlab-ci.yml
AUTHORS
ChangeLog
README.md
requirements.txt
setup.cfg
setup.py
doc/Makefile
doc/make.bat
doc/source/conf.py
doc/source/index.rst
py_appen.egg-info/PKG-INFO
py_appen.egg-info/SOURCES.txt
py_appen.egg-info/dependency_links.txt
py_appen.egg-info/not-zip-safe
py_appen.egg-info/pbr.json
py_appen.egg-info/requires.txt
py_appen.egg-info/top_level.txt
src/appen/__init__.py
src/appen/appen.py
src/appen/exceptions.py