Metadata-Version: 1.0
Name: py-appen
Version: 0.3.7
Summary: Appen APIs in a Python Friendly Form
Home-page: https://gitlab.com/mgreenberg/py-appen
Author: Matthew Greenberg
Author-email: mgreenberg@gumgum.com
License: UNKNOWN
Platform: UNKNOWN
